README.md
atac_graph.py
setup.cfg
setup.py
Atacgraph.egg-info/PKG-INFO
Atacgraph.egg-info/SOURCES.txt
Atacgraph.egg-info/dependency_links.txt
Atacgraph.egg-info/top_level.txt
script/GTF.py
script/Transcript.py
script/__init__.py
script/extract_transcript_regions.py