Metadata-Version: 1.1
Name: Atacgraph
Version: 1.0
Summary: ATAC-seq pipeline
Home-page: https://github.com/kullatnunu/atacgraph
Author: TimLiu
Author-email: t810308@gmail.com
License: UNKNOWN
Download-URL: https://github.com/kullatnunu/atacgraph.git
Keywords: atac-seq, histograme, heatmap
Platform: UNKNOWN
